dbus_fast/__init__.py
dbus_fast/__version__.py
dbus_fast/auth.py
dbus_fast/constants.py
dbus_fast/errors.py
dbus_fast/introspection.py
dbus_fast/message.cpython-311-aarch64-linux-gnu.so
dbus_fast/message.pxd
dbus_fast/message.py
dbus_fast/message_bus.cpython-311-aarch64-linux-gnu.so
dbus_fast/message_bus.pxd
dbus_fast/message_bus.py
dbus_fast/proxy_object.py
dbus_fast/py.typed
dbus_fast/send_reply.py
dbus_fast/service.cpython-311-aarch64-linux-gnu.so
dbus_fast/service.pxd
dbus_fast/service.py
dbus_fast/signature.cpython-311-aarch64-linux-gnu.so
dbus_fast/signature.pxd
dbus_fast/signature.py
dbus_fast/unpack.cpython-311-aarch64-linux-gnu.so
dbus_fast/unpack.pxd
dbus_fast/unpack.py
dbus_fast/validators.py
dbus_fast/_private/__init__.py
dbus_fast/_private/_cython_compat.py
dbus_fast/_private/address.cpython-311-aarch64-linux-gnu.so
dbus_fast/_private/address.pxd
dbus_fast/_private/address.py
dbus_fast/_private/constants.py
dbus_fast/_private/marshaller.cpython-311-aarch64-linux-gnu.so
dbus_fast/_private/marshaller.pxd
dbus_fast/_private/marshaller.py
dbus_fast/_private/unmarshaller.cpython-311-aarch64-linux-gnu.so
dbus_fast/_private/unmarshaller.pxd
dbus_fast/_private/unmarshaller.py
dbus_fast/_private/util.py
dbus_fast/aio/__init__.py
dbus_fast/aio/message_bus.py
dbus_fast/aio/message_reader.cpython-311-aarch64-linux-gnu.so
dbus_fast/aio/message_reader.pxd
dbus_fast/aio/message_reader.py
dbus_fast/aio/proxy_object.py
dbus_fast/glib/__init__.py
dbus_fast/glib/message_bus.py
dbus_fast/glib/proxy_object.py
dbus_fast-3.1.1.dist-info/METADATA
dbus_fast-3.1.1.dist-info/WHEEL
dbus_fast-3.1.1.dist-info/RECORD
dbus_fast-3.1.1.dist-info/licenses/LICENSE
